sphinxdrawio
