Metadata-Version: 2.1
Name: sphinxcontrib-drawio-html
Version: 0.1.2
Summary: Sphinx Extension to include draw.io files using HTML5 embedding
Home-page: https://github.com/gotpredictions/sphinxcontrib-drawio-html
Author: Eswar Vandanapu
Author-email: eswar.vandanapu@gmail.com
License: UNKNOWN
Platform: UNKNOWN
Classifier: Programming Language :: Python :: 3
Classifier: License :: OSI Approved :: MIT License
Classifier: Operating System :: OS Independent
Classifier: Framework :: Sphinx :: Extension
Requires-Python: >=3.7
